rotoger/__init__.py
rotoger-0.2.1.dist-info/WHEEL
rotoger-0.2.1.dist-info/entry_points.txt
rotoger-0.2.1.dist-info/METADATA
rotoger-0.2.1.dist-info/RECORD
